{
    "account": {
        "challenge": [],
        "errorStatus": false,
        "isFetching": false,
        "locakTicketStatus": false,
        "message": ""
    },
    "active": {
        "activeConfirmError": null,
        "activeConfirmSucceeded": null,
        "sendDigitsError": null
    },
    "answers": {
        "copyrightApplicants": {},
        "favlists": {},
        "newAnswer": {},
        "voters": {}
    },
    "articles": {
        "voters": {}
    },
    "banner": {},
    "captcha": {
        "captchaBase64String": null,
        "captchaNeeded": false,
        "captchaValidationMessage": null,
        "loginCaptchaExpires": false
    },
    "comments": {
        "collapsed": {},
        "conversation": {},
        "pagination": {},
        "parent": {},
        "reverse": {},
        "reviewing": {}
    },
    "config": {
        "alertTimeSpan": 3600,
        "canWrite": false,
        "isWindow": 1,
        "tip": "应国家法规对于帐号实名的要求，进行下一步操作前，需要先完成手机绑定。"
    },
    "cookie": "",
    "coupon": {
        "isRedeemingCoupon": false
    },
    "currentUser": "xziar",
    "entities": {
        "activities": {
            "1502613674": {
                "actionText": "赞同了回答",
                "actor": {
                    "avatarUrl": "https://pic3.zhimg.com/50/v2-b3dd59876e9248bdd5998b1ddb763502_s.jpg",
                    "badge": [],
                    "gender": 1,
                    "headline": "",
                    "id": "597a075e0351ef0b3b9ae4a98f03412a",
                    "isFollowed": false,
                    "isFollowing": false,
                    "isOrg": false,
                    "name": "陈元萍",
                    "type": "people",
                    "url": "https://api.zhihu.com/people/597a075e0351ef0b3b9ae4a98f03412a",
                    "urlToken": "chen-yuan-ping-65-58",
                    "userType": "people"
                },
                "createdTime": 1502613674,
                "id": "1502613674",
                "target": {
                    "id": 153380525,
                    "schema": "answer"
                },
                "type": "feed",
                "verb": "ANSWER_VOTE_UP"
            },
            "1502636196": {
                "actionText": "赞同了回答",
                "actor": {
                    "avatarUrl": "https://pic3.zhimg.com/50/v2-b3dd59876e9248bdd5998b1ddb763502_s.jpg",
                    "badge": [],
                    "gender": 1,
                    "headline": "",
                    "id": "597a075e0351ef0b3b9ae4a98f03412a",
                    "isFollowed": false,
                    "isFollowing": false,
                    "isOrg": false,
                    "name": "陈元萍",
                    "type": "people",
                    "url": "https://api.zhihu.com/people/597a075e0351ef0b3b9ae4a98f03412a",
                    "urlToken": "chen-yuan-ping-65-58",
                    "userType": "people"
                },
                "createdTime": 1502636196,
                "id": "1502636196",
                "target": {
                    "id": 213734920,
                    "schema": "answer"
                },
                "type": "feed",
                "verb": "ANSWER_VOTE_UP"
            },
            "1502713353": {
                "actionText": "赞同了回答",
                "actor": {
                    "avatarUrl": "https://pic3.zhimg.com/50/v2-b3dd59876e9248bdd5998b1ddb763502_s.jpg",
                    "badge": [],
                    "gender": 1,
                    "headline": "",
                    "id": "597a075e0351ef0b3b9ae4a98f03412a",
                    "isFollowed": false,
                    "isFollowing": false,
                    "isOrg": false,
                    "name": "陈元萍",
                    "type": "people",
                    "url": "https://api.zhihu.com/people/597a075e0351ef0b3b9ae4a98f03412a",
                    "urlToken": "chen-yuan-ping-65-58",
                    "userType": "people"
                },
                "createdTime": 1502713353,
                "id": "1502713353",
                "target": {
                    "id": 205916738,
                    "schema": "answer"
                },
                "type": "feed",
                "verb": "ANSWER_VOTE_UP"
            },
            "1502713357": {
                "actionText": "赞同了回答",
                "actor": {
                    "avatarUrl": "https://pic3.zhimg.com/50/v2-b3dd59876e9248bdd5998b1ddb763502_s.jpg",
                    "badge": [],
                    "gender": 1,
                    "headline": "",
                    "id": "597a075e0351ef0b3b9ae4a98f03412a",
                    "isFollowed": false,
                    "isFollowing": false,
                    "isOrg": false,
                    "name": "陈元萍",
                    "type": "people",
                    "url": "https://api.zhihu.com/people/597a075e0351ef0b3b9ae4a98f03412a",
                    "urlToken": "chen-yuan-ping-65-58",
                    "userType": "people"
                },
                "createdTime": 1502713357,
                "id": "1502713357",
                "target": {
                    "id": 208107176,
                    "schema": "answer"
                },
                "type": "feed",
                "verb": "ANSWER_VOTE_UP"
            },
            "1502806839": {
                "actionText": "赞同了回答",
                "actor": {
                    "avatarUrl": "https://pic3.zhimg.com/50/v2-b3dd59876e9248bdd5998b1ddb763502_s.jpg",
                    "badge": [],
                    "gender": 1,
                    "headline": "",
                    "id": "597a075e0351ef0b3b9ae4a98f03412a",
                    "isFollowed": false,
                    "isFollowing": false,
                    "isOrg": false,
                    "name": "陈元萍",
                    "type": "people",
                    "url": "https://api.zhihu.com/people/597a075e0351ef0b3b9ae4a98f03412a",
                    "urlToken": "chen-yuan-ping-65-58",
                    "userType": "people"
                },
                "createdTime": 1502806839,
                "id": "1502806839",
                "target": {
                    "id": 214859200,
                    "schema": "answer"
                },
                "type": "feed",
                "verb": "ANSWER_VOTE_UP"
            }
        },
        "answers": {
            "153380525": {
                "author": {
                    "avatarUrl": "https://pic4.zhimg.com/50/v2-08cd39fd4680ea23a2f0e0bf2f966c77_s.jpg",
                    "badge": [],
                    "gender": 1,
                    "headline": "尚马教育Java培训讲师；北京萌小猪科技技术顾问",
                    "id": "aa81915649b82af22be8616e22f905c7",
                    "isFollowed": false,
                    "isFollowing": false,
                    "isOrg": false,
                    "name": "得闲野鹤",
                    "type": "people",
                    "url": "https://api.zhihu.com/people/aa81915649b82af22be8616e22f905c7",
                    "urlToken": "Z.ylin",
                    "userType": "people"
                },
                "canComment": {
                    "reason": "",
                    "status": true
                },
                "commentCount": 68,
                "commentPermission": "all",
                "content": "<p>1.首先云计算不是一门技术,而是一颗技能树.这牵扯到虚拟化,分布式、并行计算,网络存储,负载,备份等等,这牵扯到的技术和架构思想何其庞大.</p><p>2.4个月培训java+android+大数据处理是完全不可能的.为什么这样说呢? 你千万不要告诉我大数据处理就只是告诉学生ELK怎么安装,然后怎么在kibana输入关键字点击搜索button就叫</p><p>培训了.在学生拥有一定的java基础的情况下,教大数据不应该先从lucene的原理、分词等等开始,光搜索体系认知和logstash的运行原理就得几周吧?那还有hadoop、Hbase、Phoenix、Spark这些呢? 就提个名字吗?</p><p>3.4个月把一个学生培养成java入门者,或者java中级开发者还是有可能的.从对学生进行程序开发思维培养(负载均衡到底是什么;集群解决了什么问题;M/S的作用是什么;),servlet的原理透析(Listener、Filter的能量到底有多大),spring的设计思想和运行原理(老生常谈的IOC和AOP是怎么实现的)等等相关方面进行培养,讲解目前一线互联网的架构思想和常用的技术,规划学生毕业后的学习路线图,作为一名真正的老师去帮助学生.</p><br><p>以上,这才是我认为合格的培训机构.然而现在市面上大大小小的培训机构何其多,滥竽充数的也是多到不行.作为一名7年的老程序猿,这些年来面试过各种形形色色的培训出来的人.有些</p><p>学生的水平真的是掺不忍睹,不知道那些为人师表的人让你们学历造假,经验造假,张口闭口10k到底是怎么想的.我并不是歧视培训,相反我招过且带过一些培训出来的人.说这些只是想奉劝</p><p>那些跟着广告和形象大牌找大培训机构的,其实事实并没有你想的那么美.当然并不排除他们中那些本来就乐于好学,喜欢java并学而有成的人.</p>",
                "createdTime": 1490352065,
                "excerpt": "1.首先云计算不是一门技术,而是一颗技能树.这牵扯到虚拟化,分布式、并行计算,网络存储,负载,备份等等,这牵扯到的技术和架构思想何其庞大.2.4个月培训java+android+大数据处理是完全不可能的.为什么这样说呢? 你千万不要告诉我大数据处理就只是告诉学生ELK怎么安装,然后怎么在kibana输入关键字点击搜索button就叫培训了.在学生拥有一定的java基础的情况下,教大数据不应该先从lucene的原理、分词等等开始,光搜索体系认知和logstash…",
                "excerptNew": "1.首先云计算不是一门技术,而是一颗技能树.这牵扯到虚拟化,分布式、并行计算,网络存储,负载,备份等等,这牵扯到的技术和架构思想何其庞大. 2.4个月培训java+android+大数据处理是完全不可能的.为什么这样说呢? 你千万不要告诉我大数据处理就只是告诉学生ELK怎么…",
                "id": 153380525,
                "isCopyable": false,
                "markInfos": [],
                "previewText": "",
                "previewType": "default",
                "question": {
                    "answerCount": 242,
                    "author": {
                        "avatarUrl": "https://pic2.zhimg.com/aadd7b895_s.jpg",
                        "headline": "",
                        "id": "0",
                        "name": "匿名用户",
                        "type": "people",
                        "url": "",
                        "urlToken": "",
                        "userType": "people"
                    },
                    "boundTopicIds": [
                        707,
                        3646,
                        6031,
                        14480,
                        113895
                    ],
                    "commentCount": 54,
                    "created": 1388210343,
                    "followerCount": 1781,
                    "id": 22387208,
                    "isFollowing": false,
                    "title": "Java培训机构可靠吗？",
                    "type": "question",
                    "url": "https://api.zhihu.com/questions/22387208"
                },
                "relationship": {
                    "isNothelp": false,
                    "isThanked": false,
                    "upvotedFolloweeIds": [],
                    "voting": 0
                },
                "reshipmentSettings": "disallowed",
                "thanksCount": 23,
                "thumbnail": "",
                "type": "answer",
                "updatedTime": 1492412636,
                "url": "https://api.zhihu.com/answers/153380525",
                "voteupCount": 97
            },
            "205916738": {
                "author": {
                    "avatarUrl": "https://pic1.zhimg.com/50/v2-0bfca775b1bbf1fb88a2206d4f0ad218_s.jpg",
                    "badge": [],
                    "gender": 1,
                    "headline": "不善言辞，但严谨分析命理，微信qq348175685",
                    "id": "00fae110187f2b3ffb52a2417a16a85d",
                    "isFollowed": false,
                    "isFollowing": false,
                    "isOrg": false,
                    "name": "李书贤",
                    "type": "people",
                    "url": "https://api.zhihu.com/people/00fae110187f2b3ffb52a2417a16a85d",
                    "urlToken": "li-shu-xian-63",
                    "userType": "people"
                },
                "canComment": {
                    "reason": "",
                    "status": true
                },
                "commentCount": 4,
                "commentPermission": "all",
                "content": "<p>只是八字里面的神煞，以前是童子煞来做文章，现在是桃花煞做文章，实在可笑。神煞多达几百种，用来做文章的太多了。你可以找十个出马仙，你的婚姻说法至少有6种答复，特别是对方的身高从170到185这个身高内各种答复都有。基本上大多数人都带桃花，带桃花的有异性缘。本人看的大多数没有桃花的人，反而朋友都难谈到。而且婚恋进展是否顺，这个带桃花并不是重点。</p><p>另外也没有破桃花这种法事，不管是道家还是佛家，还是不要上当受骗了。</p>",
                "createdTime": 1501391498,
                "excerpt": "只是八字里面的神煞，以前是童子煞来做文章，现在是桃花煞做文章，实在可笑。神煞多达几百种，用来做文章的太多了。你可以找十个出马仙，你的婚姻说法至少有6种答复，特别是对方的身高从170到185这个身高内各种答复都有。基本上大多数人都带桃花，带桃花的有异性缘。本人看的大多数没有桃花的人，反而朋友都难谈到。而且婚恋进展是否顺，这个带桃花并不是重点。另外也没有破桃花这种法事，不管是道家还是佛家，还是不要上当受骗…",
                "excerptNew": "只是八字里面的神煞，以前是童子煞来做文章，现在是桃花煞做文章，实在可笑。神煞多达几百种，用来做文章的太多了。你可以找十个出马仙，你的婚姻说法至少有6种答复，特别是对方的身高从170到185这个身高内各种答复都有。基本上大多数人都带桃花，带桃花的有异…",
                "id": 205916738,
                "isCopyable": false,
                "markInfos": [],
                "previewText": "只是八字里面的神煞，以前是童子煞来做文章，现在是桃花煞做文章，实在可笑。神煞多达几百种，用来做文章的太多了。你可以找十个出马仙，你的婚姻说法至少有6种答复，特别是对方的身高从170到185这个身高内各种答复都有。基本上大多数人都带桃花，带桃花的有异性缘。本人看的大多数没有桃花的人，反而朋友都难谈到。而且婚恋进展是否顺，这个带桃花并不是重点。\n另外也没有破桃花这种法事，不管是道家还是佛家，还是不要上当受骗了。",
                "previewType": "expand",
                "question": {
                    "answerCount": 4,
                    "author": {
                        "avatarUrl": "https://pic3.zhimg.com/50/v2-c5d39248ff2b49d2a5c96c32f24cdbf2_s.jpg",
                        "badge": [],
                        "gender": 1,
                        "headline": "",
                        "id": "ae1be3e5e955a124264a58a32f0fc225",
                        "isFollowed": false,
                        "isFollowing": false,
                        "isOrg": false,
                        "name": "李李李",
                        "type": "people",
                        "url": "https://api.zhihu.com/people/ae1be3e5e955a124264a58a32f0fc225",
                        "urlToken": "li-li-li-80-29",
                        "userType": "people"
                    },
                    "boundTopicIds": [
                        4370,
                        9771,
                        20124,
                        92079,
                        117485
                    ],
                    "commentCount": 4,
                    "created": 1501387068,
                    "followerCount": 9,
                    "id": 63152859,
                    "isFollowing": false,
                    "title": "堂口烧香的说我有桃花煞，并要一千法金做法事。求精通命理的胖友来解惑，这种情况是诓人的还是确实有问题？",
                    "type": "question",
                    "url": "https://api.zhihu.com/questions/63152859"
                },
                "relationship": {
                    "isNothelp": false,
                    "isThanked": false,
                    "upvotedFolloweeIds": [],
                    "voting": 0
                },
                "reshipmentSettings": "need_payment",
                "thanksCount": 0,
                "thumbnail": "",
                "type": "answer",
                "updatedTime": 1501912662,
                "url": "https://api.zhihu.com/answers/205916738",
                "voteupCount": 1
            },
            "208107176": {
                "author": {
                    "avatarUrl": "https://pic1.zhimg.com/50/v2-0bfca775b1bbf1fb88a2206d4f0ad218_s.jpg",
                    "badge": [],
                    "gender": 1,
                    "headline": "不善言辞，但严谨分析命理，微信qq348175685",
                    "id": "00fae110187f2b3ffb52a2417a16a85d",
                    "isFollowed": false,
                    "isFollowing": false,
                    "isOrg": false,
                    "name": "李书贤",
                    "type": "people",
                    "url": "https://api.zhihu.com/people/00fae110187f2b3ffb52a2417a16a85d",
                    "urlToken": "li-shu-xian-63",
                    "userType": "people"
                },
                "canComment": {
                    "reason": "",
                    "status": true
                },
                "commentCount": 2,
                "commentPermission": "all",
                "content": "<p>因为还是存在大多数年纪较小的玄学初学者，吸引人气。</p><p>真正修行中人还是比较严谨，因为考虑的问题很多，基本不会花心思去讨好卖乖。</p>",
                "createdTime": 1501746827,
                "excerpt": "因为还是存在大多数年纪较小的玄学初学者，吸引人气。真正修行中人还是比较严谨，因为考虑的问题很多，基本不会花心思去讨好卖乖。",
                "excerptNew": "因为还是存在大多数年纪较小的玄学初学者，吸引人气。\n真正修行中人还是比较严谨，因为考虑的问题很多，基本不会花心思去讨好卖乖。",
                "id": 208107176,
                "isCopyable": false,
                "markInfos": [],
                "previewText": "",
                "previewType": "no_expand",
                "question": {
                    "answerCount": 32,
                    "author": {
                        "avatarUrl": "https://pic3.zhimg.com/50/v2-3517d0c97f44b0a6757b02fc4783f0b2_s.jpg",
                        "badge": [],
                        "gender": 1,
                        "headline": "中高考文化课辅导/可口可乐/自开饭馆/美团等经历",
                        "id": "1633094d0d0143a477fd8063e23c279e",
                        "isFollowed": false,
                        "isFollowing": false,
                        "isOrg": false,
                        "name": "王大肉",
                        "type": "people",
                        "url": "https://api.zhihu.com/people/1633094d0d0143a477fd8063e23c279e",
                        "urlToken": "wang-da-rou-94",
                        "userType": "people"
                    },
                    "boundTopicIds": [
                        3539,
                        4370,
                        12528,
                        63253,
                        95710
                    ],
                    "commentCount": 1,
                    "created": 1448871130,
                    "followerCount": 137,
                    "id": 38035068,
                    "isFollowing": false,
                    "title": "为什么感觉知乎上玄学算命等板块的大师们都喜欢卖萌呢？",
                    "type": "question",
                    "url": "https://api.zhihu.com/questions/38035068"
                },
                "relationship": {
                    "isNothelp": false,
                    "isThanked": false,
                    "upvotedFolloweeIds": [],
                    "voting": 0
                },
                "reshipmentSettings": "need_payment",
                "thanksCount": 1,
                "thumbnail": "",
                "type": "answer",
                "updatedTime": 1501864132,
                "url": "https://api.zhihu.com/answers/208107176",
                "voteupCount": 2
            },
            "213734920": {
                "author": {
                    "avatarUrl": "https://pic3.zhimg.com/50/v2-a9e27179a5ba39185b27e213e5bd5b12_s.jpg",
                    "badge": [],
                    "gender": 1,
                    "headline": "护肤达人",
                    "id": "30103bb5c09c7146ea87c5d0329253da",
                    "isFollowed": false,
                    "isFollowing": false,
                    "isOrg": false,
                    "name": "一岁一礼",
                    "type": "people",
                    "url": "https://api.zhihu.com/people/30103bb5c09c7146ea87c5d0329253da",
                    "urlToken": "yisui-yili",
                    "userType": "people"
                },
                "canComment": {
                    "reason": "",
                    "status": true
                },
                "commentCount": 20,
                "commentPermission": "all",
                "content": "<p>         按理说我的领域是护肤不是这个，但是又看到我关注且欣赏了很久的姑娘被yy的渣都不剩。那好，我们来聊一聊。</p><p><br></p><p>         那个一来就拿头像说事带节奏黑李子柒模仿阿南的，老子不想给你增加热度回复你。默默的点了一个踩然后另开一楼。（嗯，默默的为我的机智点了一个赞！）</p><p><br></p><p>         一开始就把阿南一顿夸后开始踩李子柒，这么给你说吧，我看了李子柒的美拍，人家是从2016年3月份就开始发古香古食的视频了，而头像是快7月份以后才换的。在换头像名字之前，别人已经发了20几个视频了！所以，你yy的李子柒是从copy南笙开始做自媒体，这点属于造谣诽谤了吧！！</p><p><br></p><p>来，上图，我懒的圈发布时间了，明白人自己看就行。</p><p><br></p><img src=\"https://pic2.zhimg.com/v2-829a623990f8c25cd9bb42382442fa2d_b.jpg\" data-rawwidth=\"750\" data-rawheight=\"1065\" class=\"origin_image zh-lightbox-thumb\" width=\"750\" data-original=\"https://pic2.zhimg.com/v2-829a623990f8c25cd9bb42382442fa2d_r.jpg\"><p><br></p><p>下面这张是换头像和名字的时间。</p><p><br></p><img src=\"https://pic3.zhimg.com/v2-7211948cbe59ebf5a3180cb971987b5a_b.jpg\" data-rawwidth=\"750\" data-rawheight=\"880\" class=\"origin_image zh-lightbox-thumb\" width=\"750\" data-original=\"https://pic3.zhimg.com/v2-7211948cbe59ebf5a3180cb971987b5a_r.jpg\"><p><br></p><p>李子柒在美拍都很火了微博都还没有什么粉丝，那时候她应该确实没有团队的。有团队的话早就全网营销了，像办公室小野那样。她就是今年2月份一出来就全网发行。而不是半年了连微博都不发视频。。这些她微博早期的40几万粉丝都可以作证。当然，后来有次聊天才知道，我一个朋友也是早期她的美拍粉丝其中之一。就像她自己说的，</p><p><br></p><p><br></p><img src=\"https://pic2.zhimg.com/v2-c953e4d1d3b6f8fc3d507643ad2f6e6d_b.png\" data-rawwidth=\"750\" data-rawheight=\"1334\" class=\"origin_image zh-lightbox-thumb\" width=\"750\" data-original=\"https://pic2.zhimg.com/v2-c953e4d1d3b6f8fc3d507643ad2f6e6d_r.png\"><p><br></p><p>          还有评论里一群人酸这篇帖子是别人营销放出来的！那我可能就呵呵了。如果是营销团队放出来的，会让都是诋毁李子柒的回复排在前面？不早删了？是别人“团队”智商有问题？这个问题的提问者我不清楚她到底是真心只是好奇还是有人故意而为之。但是我却在回答里发现了常年黑李子柒的几张老面孔，什么“粗眉大侠”什么蠛白的。最近每条关于李子柒的消息下面都有那几个人的回复。还有更多的常年黑已经匿名了！！还有一些动不动就粉转黑的“本来我很喜欢她”但是怎么怎么的，这种人，你压根就没关注过她吧。冒充粉丝来发一些黑帖我也看到不是一回两回了！！</p><p><br></p><p>          本来呢，我对这姑娘只是单纯的喜欢，后来看到这些匿名的黑帖以及那几个常年黑，我还真就心疼起来，加上我这性格吧！我还就爱给人打报不平。</p><p>       一群人诋毁和造谣全靠自己想象“我觉得” “我认为” “我感觉“，比如：我觉得农村没有她想象的那么美好’ 然后就一定是作秀！平心而论，农村真的不是每天都是那么美好，但是人家是做自媒体，是拍视频。把美好的一面吃那么多苦拍出来免费给你看还有错了？收你钱了？逼你看了？早期她自己没有摄影师一个人自己给自己拍视频的时候，冬天冻高烧，夏天中暑，一个漂亮姑娘皮肤晒的黝黑，熬夜拍视频，熬夜剪视频，，换来的就是你们这些键盘侠在空调房里敲敲键盘的猜测和抹黑？？</p><p><br></p><p>          简简单单的拍个视频火了，现在有公司看中她并且投资她做视频了。又有人不干了，天天吃饱了没事干？我看不全是，还有一些有利益关系吧。人家视频给你呈现美好的生活你爱看不看，你爱看小森林就去看你的小森林，说的小森林的生活就不美好了？一味的跪舔日本让有些人觉得很有优越感？（看了这句别着急骂我，我也喜欢小森林，觉得那是心之向往。但我也喜欢子柒，理由是同样的。我只是单纯的看不惯一个中国人拼命的踩自己国人的东西转过身去跪舔别人的东西）</p><p><br></p><p>         火了就是营销？那我负责任的告诉你，李子柒还真特么不是，她是火了之后才有投资人找上她的，并且还不干涉内容。看到过一篇今日头条人物采访李子柒的报道，她说她的理想就是希望给后辈留些东西，等以后很多传统食物都没有人做的时候他们上网一搜，原来李子柒做过，可以看着视频学着做。等视频拍到一定的高度以后她想赚点钱就不出来了，就是这么简单的一个人！一些自己是什么东西就看别人是什么东西的人，吴京那句：“我的底线高于你的理想”送给你们！</p>",
                "createdTime": 1502633418,
                "excerpt": "按理说我的领域是护肤不是这个，但是又看到我关注且欣赏了很久的姑娘被yy的渣都不剩。那好，我们来聊一聊。 那个一来就拿头像说事带节奏黑李子柒模仿阿南的，老子不想给你增加热度回复你。默默的点了一个踩然后另开一楼。（嗯，默默的为我的机智点了一个赞！） 一开始就把阿南一顿夸后开始踩李子柒，这么给你说吧，我看了李子柒的美拍，人家是从2016年3月份就开始发古香古食的视频了，而头像是快7月份以后才换的。在换头像名字之…",
                "excerptNew": "按理说我的领域是护肤不是这个，但是又看到我关注且欣赏了很久的姑娘被yy的渣都不剩。那好，我们来聊一聊。 那个一来就拿头像说事带节奏黑李子柒模仿阿南的，老子不想给你增加热度回复你。默默的点了一个踩然后另开一楼。（嗯，默默的为我的机智点了一个赞！）…",
                "id": 213734920,
                "isCopyable": true,
                "markInfos": [],
                "previewText": "",
                "previewType": "default",
                "question": {
                    "answerCount": 69,
                    "author": {
                        "avatarUrl": "https://pic2.zhimg.com/50/v2-eeddcb0ae459b59dee7a38124896cac9_s.jpg",
                        "badge": [],
                        "gender": 0,
                        "headline": "我是明星",
                        "id": "ed5b6bae837f9ebab6c70aad30bd7264",
                        "isFollowed": false,
                        "isFollowing": false,
                        "isOrg": false,
                        "name": "banana",
                        "type": "people",
                        "url": "https://api.zhihu.com/people/ed5b6bae837f9ebab6c70aad30bd7264",
                        "urlToken": "banana-95-74",
                        "userType": "people"
                    },
                    "boundTopicIds": [
                        168,
                        6589
                    ],
                    "commentCount": 6,
                    "created": 1498185621,
                    "followerCount": 153,
                    "id": 61448084,
                    "isFollowing": false,
                    "title": "如何看待微博美食博主李子柒？",
                    "type": "question",
                    "url": "https://api.zhihu.com/questions/61448084"
                },
                "relationship": {
                    "isNothelp": false,
                    "isThanked": false,
                    "upvotedFolloweeIds": [],
                    "voting": 0
                },
                "reshipmentSettings": "allowed",
                "thanksCount": 2,
                "thumbnail": "https://pic2.zhimg.com/50/v2-829a623990f8c25cd9bb42382442fa2d_200x112.jpg",
                "type": "answer",
                "updatedTime": 1502633419,
                "url": "https://api.zhihu.com/answers/213734920",
                "voteupCount": 206
            },
            "214859200": {
                "author": {
                    "avatarUrl": "https://pic2.zhimg.com/aadd7b895_s.jpg",
                    "headline": "",
                    "id": "0",
                    "name": "匿名用户",
                    "type": "people",
                    "url": "",
                    "urlToken": "",
                    "userType": "people"
                },
                "canComment": {
                    "reason": "",
                    "status": true
                },
                "commentCount": 2,
                "commentPermission": "all",
                "content": "这篇可能很多同行会对我有意见，匿了匿了。图都是网上找的，你们自己随手一搜也都能出来，我在此只推荐不做商业用途。<br><br>neo的Monet 系列<br>这个牌子价格在韩国正规美瞳里算是很实惠的了，其中俗称的小棕环，小蓝环，小黑环，都是非常自然的，几乎不增大只是有神。<img data-rawwidth=\"720\" data-rawheight=\"1010\" src=\"https://pic3.zhimg.com/v2-eb18f90c27843870d8f895d0a91e58da_b.jpg\" class=\"origin_image zh-lightbox-thumb\" width=\"720\" data-original=\"https://pic3.zhimg.com/v2-eb18f90c27843870d8f895d0a91e58da_r.jpg\"><img data-rawwidth=\"2036\" data-rawheight=\"1526\" src=\"https://pic4.zhimg.com/v2-bcb5c3be17d8e9f77386a46815dac837_b.jpg\" class=\"origin_image zh-lightbox-thumb\" width=\"2036\" data-original=\"https://pic4.zhimg.com/v2-bcb5c3be17d8e9f77386a46815dac837_r.jpg\"><img data-rawwidth=\"800\" data-rawheight=\"800\" src=\"https://pic1.zhimg.com/v2-a448b75354403e6ec670ce950de57ec4_b.jpg\" class=\"origin_image zh-lightbox-thumb\" width=\"800\" data-original=\"https://pic1.zhimg.com/v2-a448b75354403e6ec670ce950de57ec4_r.jpg\">neo这个牌子呢，是正规老厂生产的，花纹非常多。最近不知道怎么了官方一直在提价，可能是想从薄利多销路线转变成高大上路线吧，最新官方价都到了220一副了。作为一个美瞳卖家完全不能理解，即使它工艺和花色有了很大提升。最妙的是有些同行真的就直接卖官网价220，这只是一个普通材质的美瞳，吹上天了也不值220一副。<br>而且这个牌子是假货仿货重灾区，很多二三十一幅的三无品牌都是照着neo的色板做。那种九十一百两幅的，货都拿不到，希望大家对自己的眼睛负责，看到这样的价格还是绕道吧。<br><br>ick的full moon周年系列<br><img data-rawwidth=\"960\" data-rawheight=\"960\" src=\"https://pic3.zhimg.com/v2-d186d139f443a362326fc5fac129fabe_b.jpg\" class=\"origin_image zh-lightbox-thumb\" width=\"960\" data-original=\"https://pic3.zhimg.com/v2-d186d139f443a362326fc5fac129fabe_r.jpg\"><img data-rawwidth=\"960\" data-rawheight=\"960\" src=\"https://pic4.zhimg.com/v2-d02c0e73082b08718aef55c362bdf3f3_b.jpg\" class=\"origin_image zh-lightbox-thumb\" width=\"960\" data-original=\"https://pic4.zhimg.com/v2-d02c0e73082b08718aef55c362bdf3f3_r.jpg\"><img data-rawwidth=\"960\" data-rawheight=\"960\" src=\"https://pic2.zhimg.com/v2-3c361c41596918315198e9f3cbb8c9f1_b.jpg\" class=\"origin_image zh-lightbox-thumb\" width=\"960\" data-original=\"https://pic2.zhimg.com/v2-3c361c41596918315198e9f3cbb8c9f1_r.jpg\"><img data-rawwidth=\"1005\" data-rawheight=\"960\" src=\"https://pic4.zhimg.com/v2-ef919d7a62b4fe3180eb57800672d1e3_b.jpg\" class=\"origin_image zh-lightbox-thumb\" width=\"1005\" data-original=\"https://pic4.zhimg.com/v2-ef919d7a62b4fe3180eb57800672d1e3_r.jpg\"><br><br>硅水凝胶材质，适合眼睛容易发干的人佩戴。是很多韩剧的美瞳赞助商，所以在年轻群体里比较受欢迎，比neo价格贵一些，但它是硅水凝胶材质美瞳里面性价比非常高的了，除了wanna be系列等主打高端的系列，平常的atti等系列都是很经济的。<br>divabisou mina棕<img data-rawwidth=\"934\" data-rawheight=\"683\" src=\"https://pic4.zhimg.com/v2-ada081a39f620a3cc227b4861b5c86df_b.jpg\" class=\"origin_image zh-lightbox-thumb\" width=\"934\" data-original=\"https://pic4.zhimg.com/v2-ada081a39f620a3cc227b4861b5c86df_r.jpg\"><br>也是硅水凝胶材质，这是一个中高端牌子了，但是卖家良心的话不会贵到哪里去。这个花纹真的非常自然而且不死板，我自己是一直回购的。如果你是深瞳色，带上比小棕环小黑环还要自然。我自己就是深瞳色，深瞳色相对来说比较难找到合适的美瞳，像是小黑环这种，戴在深瞳色的人眼睛上其实是比较空洞的，就一团黑色即使它的着色直径比较小。这一款外圈不是那种容易白内障的灰色，是黑度比较重的灰色，而且它内圈外圈都是虚边。信我，我戴上自然到对着家里的镜子都看不出自己戴了美瞳，对着比较强烈阳光的话能隐约看到棕色内圈。<br>浅瞳的话，浅瞳戴什么都好看好吗<br><img data-rawwidth=\"316\" data-rawheight=\"234\" src=\"https://pic4.zhimg.com/v2-39d37372b1d45c0f64a60b102f2a84b7_b.jpg\" class=\"content_image\" width=\"316\"><br>还有什么别的问题想问私信我吧kk<br><br>大概就先写这么多吧，以后有时间再补充，手机码了这么多字，大家走过路过不给我点个赞吗_(´༎`」∠)_",
                "createdTime": 1502801983,
                "excerpt": "这篇可能很多同行会对我有意见，匿了匿了。图都是网上找的，你们自己随手一搜也都能出来，我在此只推荐不做商业用途。 neo的Monet 系列 这个牌子价格在韩国正规美瞳里算是很实惠的了，其中俗称的小棕环，小蓝环，小黑环，都是非常自然的，几乎不增大只是有神。neo这个牌子呢，是正规老厂生产的，花纹非常多。最近不知道怎么了官方一直在提价，可能是想从薄利多销路线转变成高大上路线吧，最新官方价都到了220一副了。作为一个美…",
                "excerptNew": "这篇可能很多同行会对我有意见，匿了匿了。图都是网上找的，你们自己随手一搜也都能出来，我在此只推荐不做商业用途。 neo的Monet 系列 这个牌子价格在韩国正规美瞳里算是很实惠的了，其中俗称的小棕环，小蓝环，小黑环，都是非常自然的，几乎不增大只是有神。…",
                "id": 214859200,
                "isCopyable": false,
                "markInfos": [],
                "previewText": "",
                "previewType": "default",
                "question": {
                    "answerCount": 138,
                    "author": {
                        "avatarUrl": "https://pic2.zhimg.com/50/a723e0a0e2cf82a41fa6f61c61a9b825_s.jpg",
                        "badge": [],
                        "gender": 0,
                        "headline": "",
                        "id": "4e0ca7ccd55437e5688ac969b9c85374",
                        "isFollowed": false,
                        "isFollowing": false,
                        "isOrg": false,
                        "name": "logo",
                        "type": "people",
                        "url": "https://api.zhihu.com/people/4e0ca7ccd55437e5688ac969b9c85374",
                        "urlToken": "123456-29-50",
                        "userType": "people"
                    },
                    "boundTopicIds": [
                        676,
                        4792,
                        5198,
                        9403,
                        132644
                    ],
                    "commentCount": 2,
                    "created": 1456466264,
                    "followerCount": 1650,
                    "id": 40776354,
                    "isFollowing": false,
                    "title": "小直径美瞳求推荐？",
                    "type": "question",
                    "url": "https://api.zhihu.com/questions/40776354"
                },
                "relationship": {
                    "isNothelp": false,
                    "isThanked": false,
                    "upvotedFolloweeIds": [],
                    "voting": 0
                },
                "reshipmentSettings": "disallowed",
                "thanksCount": 0,
                "thumbnail": "https://pic3.zhimg.com/50/v2-eb18f90c27843870d8f895d0a91e58da_200x112.jpg",
                "type": "answer",
                "updatedTime": 1502802543,
                "url": "https://api.zhihu.com/answers/214859200",
                "voteupCount": 56
            }
        },
        "articles": {},
        "columns": {},
        "comments": {},
        "ebooks": {},
        "favlists": {},
        "feeds": {},
        "notifications": {},
        "pins": {},
        "promotions": {},
        "questions": {},
        "roundtables": {},
        "topics": {},
        "users": {
            "chen-yuan-ping-65-58": {
                "accountStatus": [
                    {
                        "createdAt": 1502849999,
                        "expiredAt": 0,
                        "name": "hang",
                        "reason": "ads"
                    }
                ],
                "allowMessage": true,
                "answerCount": 0,
                "articlesCount": 0,
                "avatarHue": "0xa7a49b",
                "avatarUrl": "https://pic3.zhimg.com/v2-b3dd59876e9248bdd5998b1ddb763502_is.jpg",
                "avatarUrlTemplate": "https://pic3.zhimg.com/v2-b3dd59876e9248bdd5998b1ddb763502_{size}.jpg",
                "badge": [],
                "columnsCount": 0,
                "commercialQuestionCount": 0,
                "coverUrl": "",
                "description": "",
                "educations": [],
                "employments": [],
                "favoriteCount": 0,
                "favoritedCount": 0,
                "followerCount": 0,
                "followingColumnsCount": 1,
                "followingCount": 3,
                "followingFavlistsCount": 0,
                "followingQuestionCount": 0,
                "followingTopicCount": 0,
                "gender": -1,
                "headline": "",
                "hostedLiveCount": 0,
                "id": "597a075e0351ef0b3b9ae4a98f03412a",
                "isActive": 1497161241,
                "isAdvertiser": false,
                "isBindSina": false,
                "isBlocked": false,
                "isBlocking": false,
                "isFollowed": false,
                "isFollowing": false,
                "isForceRenamed": false,
                "isOrg": false,
                "isPrivacyProtected": false,
                "locations": [],
                "logsCount": 0,
                "markedAnswersCount": 0,
                "markedAnswersText": "",
                "messageThreadToken": "4632502710",
                "mutualFolloweesCount": 0,
                "name": "陈元萍",
                "participatedLiveCount": 0,
                "pinsCount": 0,
                "questionCount": 0,
                "showSinaWeibo": false,
                "thankFromCount": 0,
                "thankToCount": 0,
                "thankedCount": 0,
                "type": "people",
                "url": "http://www.zhihu.com/api/v4/people/597a075e0351ef0b3b9ae4a98f03412a",
                "urlToken": "chen-yuan-ping-65-58",
                "userType": "people",
                "voteFromCount": 0,
                "voteToCount": 0,
                "voteupCount": 0
            },
            "xziar": {
                "accountStatus": [],
                "adType": "normal",
                "answerCount": 694,
                "articlesCount": 0,
                "availableMessageTypes": [
                    "common"
                ],
                "avatarUrl": "https://pic1.zhimg.com/db798e828014f5b25ba29178b43e0540_is.jpg",
                "avatarUrlTemplate": "https://pic1.zhimg.com/db798e828014f5b25ba29178b43e0540_{size}.jpg",
                "badge": [],
                "business": {
                    "avatarUrl": "https://pic1.zhimg.com/e82bab09c_is.jpg",
                    "excerpt": "徼",
                    "id": "19619368",
                    "introduction": "徼",
                    "name": "计算机软件",
                    "type": "topic",
                    "url": "http://www.zhihu.com/api/v4/topics/19619368"
                },
                "caEnabled": false,
                "canEditTopic": true,
                "coverUrl": "https://pic4.zhimg.com/v2-f0ab3a6e3ec12a6430488f6d891e93d3_b.jpg",
                "defaultNotificationsCount": 0,
                "description": "小小透明",
                "draftCount": 168,
                "editorInfo": [],
                "educations": [],
                "email": "cz****@gmail.com",
                "employments": [],
                "favoriteCount": 8,
                "favoritedCount": 218,
                "followNotificationsCount": 0,
                "followerCount": 119,
                "gender": 1,
                "headline": "介绍给谁看？",
                "id": "f76cc47c7de7323b10ece9d850514561",
                "isActive": 1,
                "isAdvertiser": false,
                "isBindPhone": true,
                "isBindSina": false,
                "isForceRenamed": false,
                "isOrg": false,
                "lastCommentPermission": "all",
                "locations": [
                    {
                        "avatarUrl": "https://pic2.zhimg.com/389a772ec26fa8910f8cea8867adef59_is.png",
                        "excerpt": "东南形胜，三吴都会，钱塘自古繁华，烟柳画桥，风帘翠幕，参差十万人家。云树绕堤沙，怒涛卷霜雪，天堑无涯。市列珠玑，户盈罗绮，竞豪奢。 重湖叠巘清嘉。有三秋桂子，十里荷花。羌管弄晴，菱歌泛夜，嬉嬉钓叟莲娃。千骑拥高牙。乘醉听箫鼓，吟赏烟霞。异日图将好景，归去凤池夸。",
                        "id": "19558830",
                        "introduction": "<p>东南形胜，三吴都会，钱塘自古繁华，烟柳画桥，风帘翠幕，参差十万人家。云树绕堤沙，怒涛卷霜雪，天堑无涯。市列珠玑，户盈罗绮，竞豪奢。<br>重湖叠巘清嘉。有三秋桂子，十里荷花。羌管弄晴，菱歌泛夜，嬉嬉钓叟莲娃。千骑拥高牙。乘醉听箫鼓，吟赏烟霞。异日图将好景，归去凤池夸。</p>",
                        "name": "杭州",
                        "type": "topic",
                        "url": "http://www.zhihu.com/api/v4/topics/19558830"
                    }
                ],
                "messagesCount": 0,
                "name": "XZiar",
                "renamedFullname": "",
                "showSinaWeibo": false,
                "thankedCount": 380,
                "type": "people",
                "uid": 59016952676352,
                "url": "http://www.zhihu.com/api/v4/people/f76cc47c7de7323b10ece9d850514561",
                "urlToken": "xziar",
                "userType": "people",
                "visitsCount": 5327,
                "voteThankNotificationsCount": 0
            }
        }
    },
    "env": {
        "edition": {
            "baidu": false,
            "yidianzixun": false
        },
        "experiment": {
            "androidProfilePanel": "panel_b",
            "answerRelatedReadings": "qa_recommend_by_algo_related_with_article",
            "default": "None",
            "favAct": "default",
            "ge2": "ge2_1",
            "ge3": "ge3_9",
            "homeNweb": "default",
            "homeUi2": "default",
            "iOSNewestVersion": "3.56.0",
            "liveStore": "ls_a3_b1_c2_f2",
            "mobileQaPageProxyHeifetz": "m_qa_page_oldweb",
            "newMore": "new",
            "nwebStickySidebar": "sticky",
            "qaStickySidebar": "sticky_sidebar",
            "qrcodeLogin": "qrcode",
            "recomAnswerRec": "recom_answer_by_question",
            "recomTopicAc": "topic_ac_with_no_reason",
            "wechatShareModal": "wechat_share_modal_show",
            "zcmLighting": "zcm"
        },
        "trafficSource": "",
        "userAgent": {
            "Android": false,
            "Edge": false,
            "Mobile": false,
            "QQ": false,
            "Wechat": false,
            "Weibo": false,
            "Zhihu": false,
            "iOS": false,
            "isAppleDevice": false,
            "isBot": false,
            "isWebView": false
        }
    },
    "explore": {
        "hotfeeds": {},
        "recommendations": {}
    },
    "favlists": {
        "relations": {}
    },
    "guide": {
        "guide": {
            "isFetching": false,
            "isShowGuide": false
        }
    },
    "loading": {
        "global": {
            "count": 0
        },
        "local": {
            "config/getAppConfig/": false,
            "currentUser/get/": false,
            "env/getExperiments/": false,
            "people/get/": false,
            "people/getActivities/chen-yuan-ping-65-58": false,
            "token/": false
        }
    },
    "login": {
        "loginConfirmError": null,
        "loginConfirmSucceeded": null,
        "qrcodeLoginError": null,
        "qrcodeLoginReturnNewToken": false,
        "qrcodeLoginScanStatus": 0,
        "qrcodeLoginToken": "",
        "sendDigitsError": null
    },
    "messages": {
        "currentTab": "common",
        "data": {},
        "messageCount": 0
    },
    "notification": {},
    "people": {
        "activitiesByUser": {
            "chen-yuan-ping-65-58": {
                "ids": [
                    "1502806839",
                    "1502713357",
                    "1502713353",
                    "1502636196",
                    "1502613674"
                ],
                "isDrained": false,
                "isFetching": false,
                "newIds": [
                    "1502806839",
                    "1502713357",
                    "1502713353",
                    "1502636196",
                    "1502613674"
                ],
                "next": "http://www.zhihu.com/api/v4/members/chen-yuan-ping-65-58/activities?limit=20&after_id=1502613674&desktop=True",
                "previous": "http://www.zhihu.com/api/v4/members/chen-yuan-ping-65-58/activities?before_id=1502806839&limit=20&desktop=True"
            }
        },
        "allFavlistsByUser": {},
        "answersByUser": {},
        "answersMarkedByUser": {},
        "answersSortByVotesByUser": {},
        "articlesByUser": {},
        "articlesSortByVotesByUser": {},
        "brands": null,
        "columnsByUser": {},
        "commercialQuestionsByUser": {},
        "favlistsByUser": {},
        "followersByUser": {},
        "followingByUser": {},
        "followingColumnsByUser": {},
        "followingFavlistsByUser": {},
        "followingQuestionsByUser": {},
        "followingTopicsByUser": {},
        "isFetching": false,
        "mutualsByUser": {},
        "pinsByUser": {},
        "publicationsByUser": {},
        "questionsByUser": {},
        "thankAnswersByUser": {},
        "thankedAnswersByUser": {},
        "topicAnswersByUser": {},
        "voteAnswersByUser": {},
        "votedAnswersByUser": {}
    },
    "pins": {
        "voters": {}
    },
    "pushNotifications": {
        "currentTab": "default",
        "default": {
            "ids": [],
            "isDrained": false,
            "isFetching": false
        },
        "follow": {
            "ids": [],
            "isDrained": false,
            "isFetching": false
        },
        "notificationsCount": {
            "default": 0,
            "follow": 0,
            "vote-thank": 0
        },
        "vote-thank": {
            "ids": [],
            "isDrained": false,
            "isFetching": false
        }
    },
    "question": {
        "answers": {},
        "bio": {},
        "brand": {},
        "collapsedAnswers": {},
        "commonAnswerCount": 0,
        "concernedFollowers": {},
        "createdAnswers": {},
        "followers": {},
        "hiddenAnswerCount": 0,
        "hiddenAnswers": {},
        "invitationCandidates": {},
        "invitees": {},
        "inviters": {},
        "notificationAnswers": {},
        "recommendReadings": {},
        "relatedLives": {},
        "similarQuestions": {}
    },
    "register": {
        "registerConfirmError": null,
        "registerConfirmSucceeded": null,
        "registerValidateErrors": {},
        "registerValidateSucceeded": null,
        "sendDigitsError": null
    },
    "reward": {},
    "shareTexts": {},
    "sms": {
        "supportedCountries": []
    },
    "switches": {},
    "token": {
        "carCompose": "2|1:0|10:1502838679|4:SZYUpkoc0tvYXh0V2E2UTBUID096dwe|92:Mi4xRXFoMUFBQUFBQUFBTU1LaHhsZmpDeWNBQUFDRUFsVk5sd3k3V1FBLUFIT3pncm5WYllhWG9qaDljaWp5dEViZXFB|73d3efbe403efb90c2c7438136f10e4779a80c2cda1f487678828f8e6f1f780d",
        "xUDID": "ADDCocZX4wuPTjD_kjRCaEa7waPBeDik5is=",
        "xsrf": "60ed832c-0ec3-4581-8f4d-4442b9ff42cd"
    },
    "topics": {
        "bios": {}
    },
    "topstory": {
        "sidebar": null,
        "topstorys": {
            "afterId": 0,
            "isDrained": false,
            "isFetching": false,
            "items": [],
            "next": null
        }
    },
    "upload": {},
    "video": {
        "data": {}
    }
}